guji/__init__.py
guji/guji.py
guji-0.2.0.dist-info/METADATA
guji-0.2.0.dist-info/WHEEL
guji-0.2.0.dist-info/entry_points.txt
guji-0.2.0.dist-info/top_level.txt
guji-0.2.0.dist-info/RECORD
