Metadata-Version: 2.1
Name: guji
Version: 0.2.0
Summary: guji guji why?
Author-email: Nicou11 <lyoungin1204@gmail.com>
License: MIT
Requires-Python: >=3.7
Requires-Dist: pytz>=2024.2
